.travis.yml
CHANGES.txt
CONTRIBUTORS.txt
README.txt
requirements.txt
setup.py
tox.ini
src/rebecca/__init__.py
src/rebecca.view.egg-info/PKG-INFO
src/rebecca.view.egg-info/SOURCES.txt
src/rebecca.view.egg-info/dependency_links.txt
src/rebecca.view.egg-info/entry_points.txt
src/rebecca.view.egg-info/namespace_packages.txt
src/rebecca.view.egg-info/not-zip-safe
src/rebecca.view.egg-info/requires.txt
src/rebecca.view.egg-info/top_level.txt
src/rebecca/view/__init__.py
tests/test_views.py